landinggear/__init__.py
landinggear/__main__.py
landinggear/base.py
landinggear/command.py
landinggear/extract_packages.py
landinggear/httpcache.py
landinggear/wheelcache.py
landinggear/tests/__init__.py
landinggear/tests/helpers.py
landinggear/tests/test_wheelcache.py
landinggear-0.0.2.dist-info/DESCRIPTION.rst
landinggear-0.0.2.dist-info/entry_points.txt
landinggear-0.0.2.dist-info/METADATA
landinggear-0.0.2.dist-info/metadata.json
landinggear-0.0.2.dist-info/RECORD
landinggear-0.0.2.dist-info/top_level.txt
landinggear-0.0.2.dist-info/WHEEL
