Metadata-Version: 2.0
Name: landinggear
Version: 0.0.2
Summary: Wheels for aeroplanes: a tool to extract packages from the pip cache.
Home-page: https://github.com/jerith/landinggear
Author: Jeremy Thurgood
Author-email: firxen@gmail.com
License: MIT
Keywords: pip,wheel,aeroplane,cache
Platform: UNKNOWN
Classifier: Development Status :: 3 - Alpha
Classifier: Environment :: Console
Classifier: Intended Audience :: Developers
Classifier: License :: OSI Approved :: MIT License
Classifier: Operating System :: POSIX
Classifier: Programming Language :: Python
Classifier: Topic :: Software Development
Requires-Dist: pip
Requires-Dist: wheel
